<?xml version="1.0" encoding="utf-8"?>
<!-- 创建时间:21-09-23 10:28:10 -->
<content>
	<SlopeAssembly version="4.00" software="Eicad"/>
	<BreakChain string=""/>
	<Slope>
		<SlopeLine name="垂直交地线" type="0" color="45" draw="0" dashed="0" compute="1">
			<Settings FixedType="4" fixed="1.50000" end_flag="0" end_ctrl="0" end_value="3.000" ctrl_str="" qbt="0" prot="0" dq_file=""/>
			<DQPoints/>
			<End_Condition end="0" cdt0="0" cdt1="0" cdtv="0.000" cdta="0" JumpIndex="1"/>
			<Options  drawT="0" start_t="0.000" end_t="0.000" fillet="0.000" spx="0" bpx="0" dim_offset="0" dim_slope="0"/>
		</SlopeLine>
	</Slope>
</content>
